autocreateapp/__init__.py
autocreateapp/create_project.py
autocreateapp-0.4.dist-info/METADATA
autocreateapp-0.4.dist-info/WHEEL
autocreateapp-0.4.dist-info/entry_points.txt
autocreateapp-0.4.dist-info/top_level.txt
autocreateapp-0.4.dist-info/RECORD
