Metadata-Version: 2.1
Name: autocreateapp
Version: 0.4
Summary: UNKNOWN
Home-page: UNKNOWN
License: UNKNOWN
Platform: UNKNOWN
Requires-Dist: Django
